{
  "allowCompoundWords": true,
  "caseSensitive": false,
  "ignorePaths": [
    ".vscode",
    "**/.devcontainer/**",
    "**/.git/**",
    "**/.pnpm-lock.json",
    "**/node_modules/**",
    "**/vscode-extension/**",
    "megalinter",
    "package-lock.json",
    "report"
  ],
  "language": "en,en-GB",
  "useGitignore": true,
  "noConfigSearch": true,
  "version": "0.2",
  "words": [
    "abzu",
    "amcat",
    "aztez",
    "bayonetta",
    "canva",
    "cataclismo",
    "deponia",
    "dlcs",
    "eternights",
    "faeria",
    "gnog",
    "goty",
    "janky",
    "janosik",
    "kena",
    "khazan",
    "lacto",
    "lutris",
    "megalinter",
    "mihir",
    "mihir's",
    "mihirr",
    "minit",
    "mrdgh",
    "nier",
    "nioh",
    "nooooooo",
    "oxsecurity",
    "qdcsno",
    "qora",
    "rabade",
    "relicta",
    "saatvik",
    "soulstice",
    "stefanzweifel",
    "subnautica",
    "swordigo",
    "syberia",
    "ubisoft",
    "udemy",
    "venv",
    "vergil",
    "xclip"
  ]
}
